{
  "scenes": [
    {
      "id": 1,
      "title": "La sveglia",
      "description": "à",
      "image": "http://localhost:3001/uploads/1759421107882-IMG-20251002-WA0015.jpg",
      "video": "",
      "choices": [
        {
          "id": 1,
          "text": "Inizia l'avventura",
          "nextSceneId": 2
        },
        {
          "id": 2,
          "text": "Avanti",
          "nextSceneId": 4
        }
      ],
      "isFinal": false,
      "updatedAt": "2025-10-03T16:21:33.070Z",
      "titleStyle": "",
      "titleColor": "#ffffff",
      "backgroundTheme": "",
      "effects": {
        "particles": false,
        "glow": false,
        "typewriter": false
      },
      "lastModified": "2025-10-03T18:28:05.852Z"
    },
    {
      "id": 2,
      "title": "polli",
      "description": "jjjjjjjjjjjjjjjjj",
      "image": "",
      "video": "",
      "choices": [
        {
          "id": 1759327426893,
          "text": "hhhh",
          "nextSceneId": 3
        },
        {
          "id": 1759327437958,
          "text": "bbbbb",
          "nextSceneId": 3
        }
      ],
      "isFinal": false,
      "titleStyle": "",
      "titleColor": "#ffffff",
      "backgroundTheme": "",
      "effects": {
        "particles": false,
        "glow": false,
        "typewriter": false
      },
      "lastModified": "2025-10-03T15:55:22.939Z",
      "updatedAt": "2025-10-03T15:55:22.949Z"
    },
    {
      "id": 3,
      "title": "morto",
      "description": "dddddddddddddd",
      "image": "",
      "video": "",
      "choices": [],
      "isFinal": true,
      "titleStyle": "",
      "titleColor": "#ffffff",
      "backgroundTheme": "",
      "effects": {
        "particles": false,
        "glow": false,
        "typewriter": false
      },
      "lastModified": "2025-10-03T15:55:28.562Z"
    },
    {
      "id": 4,
      "title": "Nuova Scena",
      "description": "",
      "image": "",
      "video": "",
      "choices": [],
      "isFinal": false,
      "createdAt": "2025-10-03T16:15:31.857Z"
    }
  ],
  "settings": {
    "gameName": "Il Gioco dei Trenta",
    "welcomeMessage": "Benvenuto nel gioco!",
    "maxScenes": 30,
    "theme": "unlock30"
  },
  "stats": {
    "totalScenes": 4,
    "lastModified": "2025-10-03T18:28:07.497Z",
    "forceSaveBy": "admin"
  }
}