{
  "scenes": [
    {
      "id": 28,
      "title": "Nuova Scena",
      "description": "",
      "image": "",
      "video": "",
      "choices": [],
      "isFinal": false,
      "createdAt": "2025-10-04T09:12:55.867Z"
    },
    {
      "id": 35,
      "title": "La percorri cercando di svoltare a destra ma un buco multidimensionale ha reso tutte le stradine a senso unico",
      "description": "",
      "image": "",
      "video": "",
      "choices": [
        {
          "id": 1759569498610,
          "text": "Avanti",
          "nextSceneId": 36
        }
      ],
      "isFinal": false,
      "createdAt": "2025-10-04T09:18:00.229Z",
      "titleStyle": "",
      "titleColor": "#ffffff",
      "backgroundTheme": "",
      "effects": {
        "particles": false,
        "glow": false,
        "typewriter": false
      },
      "lastModified": "2025-10-04T09:18:20.812Z",
      "updatedAt": "2025-10-04T09:18:20.813Z"
    },
    {
      "id": 36,
      "title": "Giri in tondo per sempre",
      "description": "",
      "image": "",
      "video": "",
      "choices": [
        {
          "id": 1759569513966,
          "text": "Avanti",
          "nextSceneId": 37
        }
      ],
      "isFinal": false,
      "createdAt": "2025-10-04T09:18:20.511Z",
      "titleStyle": "",
      "titleColor": "#ffffff",
      "backgroundTheme": "",
      "effects": {
        "particles": false,
        "glow": false,
        "typewriter": false
      },
      "lastModified": "2025-10-04T09:18:42.511Z",
      "updatedAt": "2025-10-04T09:18:42.512Z"
    },
    {
      "id": 37,
      "title": "YOU DEFEAT",
      "description": "",
      "image": "",
      "video": "",
      "choices": [],
      "isFinal": false,
      "createdAt": "2025-10-04T09:18:42.210Z",
      "titleStyle": "",
      "titleColor": "#ffffff",
      "backgroundTheme": "",
      "effects": {
        "particles": false,
        "glow": false,
        "typewriter": false
      },
      "lastModified": "2025-10-04T09:18:48.824Z",
      "updatedAt": "2025-10-04T09:18:48.825Z"
    }
  ],
  "settings": {
    "gameName": "Il Gioco dei Trenta",
    "welcomeMessage": "Benvenuto nel gioco!",
    "maxScenes": 999,
    "theme": "unlock30"
  },
  "stats": {
    "totalScenes": 4,
    "lastModified": "2025-10-04T09:18:48.826Z"
  }
}